<editor>
    <help>/commander/pages/@PLUGIN_NAME@/@PLUGIN_KEY@_help?s=Administration&amp;ss=Plugins#UndeployApp</help>
    <label>Application Server - JBoss UndeployApp</label>
    <version>@PLUGIN_VERSION@</version>
    <description>Undeploy an application in JBoss server.</description>
    
    <formElement>
        <type>entry</type>
        <label>Server configuration name:</label>
        <property>serverconfig</property>
        <required>1</required>
        <documentation>Supply the configuration name of the JBoss server. To view or create a new configuration, go to the Administration -> Plugins tab, and select 'Configure' action for @PLUGIN_KEY@ plugin.</documentation>
        <htmlDocumentation>Supply the configuration name of the JBoss server.<br/><br/>A Configuration defines connection details and can be created by going to plugin <a style="text-decoration: none !important; border-bottom-style: dashed; border-bottom-width: thin; font-size: inherit; color: inherit; font-family: inherit; border-color: #d8d8d8; border-spacing: 2px;" target="_blank" href="/commander/pages/@PLUGIN_NAME@/configurations">configuration page</a>.</htmlDocumentation>
    </formElement>

    <formElement>
        <type>entry</type>
        <label>Physical location of the jboss client script:</label>
        <property>scriptphysicalpath</property>
        <required>1</required>
        <documentation>Provide the physical location of the jboss Command Line Interface script, i.e: 'jboss-cli.bat', '/path/to/jboss-cli.sh'.</documentation>
    </formElement>

    <formElement>
        <type>entry</type>
        <label>Deployment Name:</label>
        <property>appname</property>
        <required>1</required>
        <documentation>Unique name of the deployment to undeploy.</documentation>
    </formElement>      
    <formElement>
        <type>checkbox</type>
        <label>Apply undeploy to all server groups:</label>
        <property>allrelevantservergroups</property>
        <checkedValue>1</checkedValue>
        <uncheckedValue>0</uncheckedValue>
        <initiallyChecked>0</initiallyChecked>
        <documentation>Select this option to apply undeploy to all server groups in which the deployment is enabled. Either server-groups or all-relevant-server-groups is required in domain mode. This argument is not applicable in standalone mode.</documentation>
    </formElement>          
    <formElement>
        <type>entry</type>
        <label>Server groups to apply:</label>
        <property>servergroups</property>
        <required>0</required>
        <documentation>Provide the comma-separated list of server group names the undeploy command applies to.</documentation>
    </formElement>
    <formElement>
        <type>checkbox</type>
        <label>Keep content:</label>
        <property>keepcontent</property>
        <checkedValue>1</checkedValue>
        <uncheckedValue>0</uncheckedValue>
        <initiallyChecked>0</initiallyChecked>
        <documentation>Select this option to disable the deployment and keep the content of the deployment, or unselect it to disable the deployment and removes its content from the repository.</documentation>
    </formElement>                  
</editor>
